pymatgen/db/__init__.py
pymatgen/db/aliases.json
pymatgen/db/config.py
pymatgen/db/creator.py
pymatgen/db/matproj.py
pymatgen/db/query_engine.py
pymatgen/db/util.py
pymatgen/db/__pycache__/__init__.cpython-39.pyc
pymatgen/db/__pycache__/config.cpython-39.pyc
pymatgen/db/__pycache__/creator.cpython-39.pyc
pymatgen/db/__pycache__/matproj.cpython-39.pyc
pymatgen/db/__pycache__/query_engine.cpython-39.pyc
pymatgen/db/__pycache__/util.cpython-39.pyc
pymatgen/db/alchemy/__init__.py
pymatgen/db/alchemy/transmuters.py
pymatgen/db/alchemy/__pycache__/__init__.cpython-39.pyc
pymatgen/db/alchemy/__pycache__/transmuters.cpython-39.pyc
pymatgen/db/alchemy/tests/__init__.py
pymatgen/db/alchemy/tests/test_transmuters.py
pymatgen/db/tests/__init__.py
pymatgen/db/tests/common.py
pymatgen/db/tests/test_creator_and_query_engine.py
pymatgen/db/tests/test_matproj.py
pymatgen/db/tests/test_query_engine.py
pymatgen/db/tests/test_queryr_engine.py
pymatgen_db-2023.7.18.data/scripts/mgbuild
pymatgen_db-2023.7.18.data/scripts/mgbuild-tbx
pymatgen_db-2023.7.18.data/scripts/mgdb
pymatgen_db-2023.7.18.data/scripts/mgvv
pymatgen_db-2023.7.18.dist-info/LICENSE
pymatgen_db-2023.7.18.dist-info/METADATA
pymatgen_db-2023.7.18.dist-info/WHEEL
pymatgen_db-2023.7.18.dist-info/top_level.txt
pymatgen_db-2023.7.18.dist-info/RECORD
