Metadata-Version: 2.1
Name: pymatgen-db
Version: 2023.7.18
Summary: Pymatgen-db is a database add-on for the Python Materials Genomics (pymatgen) materials analysis library.
Home-page: https://github.com/materialsproject/pymatgen-db
Author: Shyue Ping Ong
Author-email: shyuep@gmail.com
Maintainer: Shyue Ping Ong
Maintainer-email: shyuep@gmail.com
License: MIT
Keywords: vasp,gaussian,materials,project,electronic,structure,mongo
Classifier: Programming Language :: Python :: 3
Classifier: Programming Language :: Python :: 3.7
Classifier: Programming Language :: Python :: 3.8
Classifier: Development Status :: 4 - Beta
Classifier: Intended Audience :: Science/Research
Classifier: License :: OSI Approved :: MIT License
Classifier: Operating System :: OS Independent
Classifier: Topic :: Scientific/Engineering :: Information Analysis
Classifier: Topic :: Scientific/Engineering :: Physics
Classifier: Topic :: Scientific/Engineering :: Chemistry
Classifier: Topic :: Software Development :: Libraries :: Python Modules
Classifier: Topic :: Database
License-File: LICENSE
Requires-Dist: pymatgen (>=2022.0.3)
Requires-Dist: monty (>=0.9.6)
Requires-Dist: pymongo (>=2.8)
Provides-Extra: tests
Requires-Dist: mongomock ; extra == 'tests'
